setup.py
ble/__init__.py
ble.egg-info/PKG-INFO
ble.egg-info/SOURCES.txt
ble.egg-info/dependency_links.txt
ble.egg-info/top_level.txt