Metadata-Version: 1.0
Name: ble
Version: 0
Summary: Library to simplify interaction with Bluetooth LE controllers and OS frameworks
Home-page: https://pypi.python.org/pypi/ble
Author: Nathan L. Conrad
Author-email: nathan@noreply.alt-teknik.com
License: GNU Lesser General Public License, Version 3
